Adders/ALU's/ALU_4Bit/4Bit_ALU.v
module ALU_4bit(f,a,b,op);
input [3:0] a,b;
input [1:0] op;
output reg [3:0] f;
parameter ADD = 2'b00, SUB = 2'b01, MUL = 2'b10, DIV = 2'b11;
always @ (*)
begin
    case (op)
        ADD: f = a + b;
        SUB: f = a - b;
        MUL: f = a * b;
        DIV: f = a / b;
    endcase
end
endmodule

Adders/ALU's/ALU_4Bit/4Bit_AlU_tb.v
`include "4Bit_AlU.v"
`timescale 1ps/1ps
module Bit_AlU_tb;
reg [3:0] a,b;  
reg [1:0] op;
wire [3:0] f;
parameter ADD = 2'b00, SUB = 2'b01, MUL = 2'b10, DIV = 2'b11;
ALU_4bit DUT(f,a,b,op);   
initial
begin
    $dumpfile("4Bit_AlU_tb.vcd");
    $dumpvars(0,Bit_AlU_tb);
    $monitor("a=%b, b=%b, op=%b, f=%b",a,b,op,f);
    a = 4'b0000; b = 4'b0000; op = ADD; #10;
    a = 4'b0000; b = 4'b0001; op = ADD; #10;
    a = 4'b0001; b = 4'b0000; op = ADD; #10;
    a = 4'b0001; b = 4'b0001; op = ADD; #10;
    a = 4'b0000; b = 4'b0000; op = SUB; #10;
    a = 4'b0000; b = 4'b0001; op = SUB; #10;
    a = 4'b0001; b = 4'b0000; op = SUB; #10;
    a = 4'b0001; b = 4'b0001; op = SUB; #10;
    a = 4'b0000; b = 4'b0000; op = MUL; #10;
    a = 4'b0000; b = 4'b0001; op = MUL; #10;
    a = 4'b0001; b = 4'b0000; op = MUL; #10;
    a = 4'b0001; b = 4'b0001; op = MUL; #10;
    a = 4'b0000; b = 4'b0000; op = DIV; #10;
    a = 4'b0000; b = 4'b0001; op = DIV; #10;
    a = 4'b0001; b = 4'b0000; op = DIV; #10;
    a = 4'b0001; b = 4'b0001; op = DIV; #10;
end
endmodule

Adders/ALU's/ALU_4Bit/4Bit_AlU_tb.vcd
$date
	Sat Sep 23 18:25:42 2023
$end
$version
	Icarus Verilog
$end
$timescale
	1ps
$end
$scope module Bit_AlU_tb $end
$var wire 4 ! f [3:0] $end
$var reg 4 " a [3:0] $end
$var reg 4 # b [3:0] $end
$var reg 2 $ op [1:0] $end
$scope module DUT $end
$var wire 4 % a [3:0] $end
$var wire 4 & b [3:0] $end
$var wire 2 ' op [1:0] $end
$var reg 4 ( f [3:0] $end
$upscope $end
$upscope $end
$enddefinitions $end
#0
$dumpvars
b0 (
b0 '
b0 &
b0 %
b0 $
b0 #
b0 "
b0 !
$end
#10
b1 !
b1 (
b1 #
b1 &
#20
b0 #
b0 &
b1 "
b1 %
#30
b10 !
b10 (
b1 #
b1 &
#40
b0 !
b0 (
b1 $
b1 '
b0 #
b0 &
b0 "
b0 %
#50
b1111 !
b1111 (
b1 #
b1 &
#60
b1 !
b1 (
b0 #
b0 &
b1 "
b1 %
#70
b0 !
b0 (
b1 #
b1 &
#80
b10 $
b10 '
b0 #
b0 &
b0 "
b0 %
#90
b1 #
b1 &
#100
b0 #
b0 &
b1 "
b1 %
#110
b1 !
b1 (
b1 #
b1 &
#120
bx !
bx (
b11 $
b11 '
b0 #
b0 &
b0 "
b0 %
#130
b0 !
b0 (
b1 #
b1 &
#140
bx !
bx (
b0 #
b0 &
b1 "
b1 %
#150
b1 !
b1 (
b1 #
b1 &
