Examples/Generate/Ripple_Carry/GenerateRipplecarry.v
module RCA_G(carry_out, sum_out, a, b, carry_in);
parameter N = 8 ;
input [N-1:0] a, b;
input carry_in;
output [N-1:0] sum_out;
wire [N:0] carry ;
output carry_out;
assign carry[0] = carry_in;
assign carry_out = carry[N];
genvar i;
generate for (i = 0; i < N; i = i + 1)
    begin
        wire t1, t2, t3;
        xor g1 (t1, a[i], b[i]);
        xor g2 (sum_out[i], t1, carry[i]);
        and g3 (t2, a[i], b[i]);
        and g4 (t3, t1, carry[i]);
        or  g5 (carry[i+1], t2, t3);
    end
endgenerate
endmodule

Examples/Generate/Ripple_Carry/GenerateRipplecarry_tb.v
`include "GenerateRipplecarry.v"
`timescale 10ns/1ns
module GenerateRipplecarry_tb;
parameter N = 8 ;
reg  [N-1:0] a, b;
reg carry_in;
wire [N-1:0] sum_out;
wire [N:0] carry ;
wire carry_out;
RCA_G dut(carry_out, sum_out, a, b, carry_in);
initial begin
    $dumpfile("GenerateRipplecarry_tb.vcd");
    $dumpvars(0, GenerateRipplecarry_tb);
    $monitor("a=%d, b=%d, carry_in=%b, sum_out=%d, carry_out=%b", a, b, carry_in, sum_out, carry_out);
    a = 0; b = 0; carry_in = 0;
    #10 a = 1; b = 1; carry_in = 0;
    #10 a = 2; b = 2; carry_in = 0;
    #10 a = 3; b = 3; carry_in = 0;
    #10 a = 11; b = 11; carry_in = 0;
    #10 a = 22; b = 22; carry_in = 0;
    #10 a = 32; b = 32; carry_in = 0;
    #10 a = 32; b = 32; carry_in = 1;
    #10 a = 32; b = 0; carry_in = 1;
    #10 a = 32; b = 1; carry_in = 1;
 /*   #10 a = 10; b = 10; carry_in = 0 ;
    #10 a = 11; b = 11; carry_in = 0 ;
    #10 a = 12; b = 12; carry_in = 0 ;
    #10 a = 13; b = 13; carry_in = 0 ;
    #10 a = 14; b = 14; carry_in = 0 ;
    #10 a = 15; b = 15; carry_in = 0 ;
    #10 a = 16; b = 16; carry_in = 0 ;
    #10 a = 17; b = 17; carry_in = 0 ;
    #10 a = 18; b = 18; carry_in = 0 ;
    #10 a = 19; b = 19; carry_in = 0 ;
    #10 a = 20; b = 20; carry_in = 0 ;   */
end
endmodule

Examples/Generate/Ripple_Carry/GenerateRipplecarry_tb.vcd
$date
	Thu Sep 28 20:18:33 2023
$end
$version
	Icarus Verilog
$end
$timescale
	1ns
$end
$scope module GenerateRipplecarry_tb $end
$var wire 8 ! sum_out [7:0] $end
$var wire 1 " carry_out $end
$var reg 8 # a [7:0] $end
$var reg 8 $ b [7:0] $end
$var reg 1 % carry_in $end
$scope module dut $end
$var wire 8 & a [7:0] $end
$var wire 8 ' b [7:0] $end
$var wire 1 % carry_in $end
$var wire 8 ( sum_out [7:0] $end
$var wire 1 " carry_out $end
$var wire 9 ) carry [8:0] $end
$scope begin genblk1[0] $end
$var wire 1 * t1 $end
$var wire 1 + t2 $end
$var wire 1 , t3 $end
$upscope $end
$scope begin genblk1[1] $end
$var wire 1 - t1 $end
$var wire 1 . t2 $end
$var wire 1 / t3 $end
$upscope $end
$scope begin genblk1[2] $end
$var wire 1 0 t1 $end
$var wire 1 1 t2 $end
$var wire 1 2 t3 $end
$upscope $end
$scope begin genblk1[3] $end
$var wire 1 3 t1 $end
$var wire 1 4 t2 $end
$var wire 1 5 t3 $end
$upscope $end
$scope begin genblk1[4] $end
$var wire 1 6 t1 $end
$var wire 1 7 t2 $end
$var wire 1 8 t3 $end
$upscope $end
$scope begin genblk1[5] $end
$var wire 1 9 t1 $end
$var wire 1 : t2 $end
$var wire 1 ; t3 $end
$upscope $end
$scope begin genblk1[6] $end
$var wire 1 < t1 $end
$var wire 1 = t2 $end
$var wire 1 > t3 $end
$upscope $end
$scope begin genblk1[7] $end
$var wire 1 ? t1 $end
$var wire 1 @ t2 $end
$var wire 1 A t3 $end
$upscope $end
$upscope $end
$upscope $end
$enddefinitions $end
#0
$dumpvars
0A
0@
0?
0>
0=
0<
0;
0:
09
08
07
06
05
04
03
02
01
00
0/
0.
0-
0,
0+
0*
b0 )
b0 (
b0 '
b0 &
0%
b0 $
b0 #
0"
b0 !
$end
#100
b10 !
b10 (
b10 )
1+
b1 $
b1 '
b1 #
b1 &
#200
b100 !
b100 (
b100 )
0+
1.
b10 $
b10 '
b10 #
b10 &
#300
b110 !
b110 (
b110 )
1+
b11 $
b11 '
b11 #
b11 &
#400
b10110 !
b10110 (
b10110 )
14
b1011 $
b1011 '
b1011 #
b1011 &
#500
b101100 !
b101100 (
b101100 )
0+
11
04
17
b10110 $
b10110 '
b10110 #
b10110 &
#600
b1000000 !
b1000000 (
b1000000 )
0.
01
07
1:
b100000 $
b100000 '
b100000 #
b100000 &
#700
b1000001 !
b1000001 (
b1000001 )
1%
#800
b100001 !
b100001 (
b1 )
19
0:
b0 $
b0 '
#900
b11 )
b100010 !
b100010 (
1,
1*
b1 $
b1 '
